{
  "version": "7",
  "dialect": "postgresql",
  "entries": [
    {
      "idx": 0,
      "version": "7",
      "when": 1784788081208,
      "tag": "0000_lame_gwen_stacy",
      "breakpoints": true
    },
    {
      "idx": 1,
      "version": "7",
      "when": 1784818629802,
      "tag": "0001_amazing_hammerhead",
      "breakpoints": true
    },
    {
      "idx": 2,
      "version": "7",
      "when": 1784821331274,
      "tag": "0002_free_sugar_man",
      "breakpoints": true
    },
    {
      "idx": 3,
      "version": "7",
      "when": 1784826108152,
      "tag": "0003_fluffy_synch",
      "breakpoints": true
    },
    {
      "idx": 4,
      "version": "7",
      "when": 1784826157401,
      "tag": "0004_jittery_boomerang",
      "breakpoints": true
    }
  ]
}